LICENSE
MANIFEST.in
README.rst
setup.py
django_unihandecodejs.egg-info/PKG-INFO
django_unihandecodejs.egg-info/SOURCES.txt
django_unihandecodejs.egg-info/dependency_links.txt
django_unihandecodejs.egg-info/not-zip-safe
django_unihandecodejs.egg-info/top_level.txt
unihandecodejs/__init__.py
unihandecodejs/admin.py
unihandecodejs/models.py
unihandecodejs/tests.py
unihandecodejs/views.py
unihandecodejs/static/unihandecodejs/unihandecode-1.0.0.core.min.js
unihandecodejs/static/unihandecodejs/unihandecode-1.0.0.diacritic.min.js
unihandecodejs/static/unihandecodejs/unihandecode-1.0.0.ja.min.js
unihandecodejs/static/unihandecodejs/unihandecode-1.0.0.kr.min.js
unihandecodejs/static/unihandecodejs/unihandecode-1.0.0.vn.min.js
unihandecodejs/static/unihandecodejs/unihandecode-1.0.0.zh.min.js