Metadata-Version: 1.0
Name: django-unihandecodejs
Version: 0.1.0
Summary: A Django app that simply provides unihandecode.js (https://github.com/ojii/unihandecode.js) out of box to be used along side with Django CMS.
Home-page: https://github.com/georgema1982/django-unihandecode
Author: George Ma
Author-email: george.ma1982@gmail.com
License: GPLv3/Perl
Platform: UNKNOWN
Classifier: Development Status :: 3 - Alpha
Classifier: Framework :: Django
Classifier: Intended Audience :: Developers
Classifier: License :: OSI Approved :: GNU General Public License v3 (GPLv3)
Classifier: Operating System :: OS Independent
Classifier: Programming Language :: Python
Classifier: Topic :: Internet :: WWW/HTTP
